Workbook

Sheet Summary
A1: SmartCart — Full Stack E-Commerce Web Application
A2: Software Test Case Document
A4: Project Name: | B4: SmartCart – Full Stack E-Commerce Web Application
A5: Prepared By: | B5: Darshan Takarkhede
A6: Submitted For: | B6: Full Stack Java Development Certification – SPRK Technologies
A7: Test Environment: | B7: Production (Vercel + Render + Railway) and local development
A8: Testing Type: | B8: Manual functional testing
A9: Date: | B9: August 2026
A11: Test Execution Summary
A12: Total Test Cases | B12: Passed | C12: Failed | D12: Pass Rate
A13: =COUNTA('Test Cases'!A3:A1000) -> 51 | B13: =COUNTIF('Test Cases'!I3:I1000,"Pass") -> 51 | C13: =COUNTIF('Test Cases'!I3:I1000,"Fail") -> 0 | D13: =IFERROR(B13/A13,0) -> 1
A16: Results by Module
A17: Module | B17: Total | C17: Passed | D17: Failed | E17: Pass Rate
A18: Authentication | B18: =COUNTIF('Test Cases'!B3:B1000,A18) -> 6 | C18: =COUNTIFS('Test Cases'!B3:B1000,A18,'Test Cases'!I3:I1000,"Pass") -> 6 | D18: =COUNTIFS('Test Cases'!B3:B1000,A18,'Test Cases'!I3:I1000,"Fail") -> 0 | E18: =IFERROR(C18/B18,0) -> 1
A19: Security & Authorization | B19: =COUNTIF('Test Cases'!B3:B1000,A19) -> 5 | C19: =COUNTIFS('Test Cases'!B3:B1000,A19,'Test Cases'!I3:I1000,"Pass") -> 5 | D19: =COUNTIFS('Test Cases'!B3:B1000,A19,'Test Cases'!I3:I1000,"Fail") -> 0 | E19: =IFERROR(C19/B19,0) -> 1
A20: Product Management | B20: =COUNTIF('Test Cases'!B3:B1000,A20) -> 7 | C20: =COUNTIFS('Test Cases'!B3:B1000,A20,'Test Cases'!I3:I1000,"Pass") -> 7 | D20: =COUNTIFS('Test Cases'!B3:B1000,A20,'Test Cases'!I3:I1000,"Fail") -> 0 | E20: =IFERROR(C20/B20,0) -> 1
A21: Category Management | B21: =COUNTIF('Test Cases'!B3:B1000,A21) -> 2 | C21: =COUNTIFS('Test Cases'!B3:B1000,A21,'Test Cases'!I3:I1000,"Pass") -> 2 | D21: =COUNTIFS('Test Cases'!B3:B1000,A21,'Test Cases'!I3:I1000,"Fail") -> 0 | E21: =IFERROR(C21/B21,0) -> 1
A22: Search, Filter & Pagination | B22: =COUNTIF('Test Cases'!B3:B1000,A22) -> 5 | C22: =COUNTIFS('Test Cases'!B3:B1000,A22,'Test Cases'!I3:I1000,"Pass") -> 5 | D22: =COUNTIFS('Test Cases'!B3:B1000,A22,'Test Cases'!I3:I1000,"Fail") -> 0 | E22: =IFERROR(C22/B22,0) -> 1
A23: Cart & Wishlist | B23: =COUNTIF('Test Cases'!B3:B1000,A23) -> 5 | C23: =COUNTIFS('Test Cases'!B3:B1000,A23,'Test Cases'!I3:I1000,"Pass") -> 5 | D23: =COUNTIFS('Test Cases'!B3:B1000,A23,'Test Cases'!I3:I1000,"Fail") -> 0 | E23: =IFERROR(C23/B23,0) -> 1
A24: Coupons & Checkout | B24: =COUNTIF('Test Cases'!B3:B1000,A24) -> 4 | C24: =COUNTIFS('Test Cases'!B3:B1000,A24,'Test Cases'!I3:I1000,"Pass") -> 4 | D24: =COUNTIFS('Test Cases'!B3:B1000,A24,'Test Cases'!I3:I1000,"Fail") -> 0 | E24: =IFERROR(C24/B24,0) -> 1
A25: Orders & Invoicing | B25: =COUNTIF('Test Cases'!B3:B1000,A25) -> 4 | C25: =COUNTIFS('Test Cases'!B3:B1000,A25,'Test Cases'!I3:I1000,"Pass") -> 4 | D25: =COUNTIFS('Test Cases'!B3:B1000,A25,'Test Cases'!I3:I1000,"Fail") -> 0 | E25: =IFERROR(C25/B25,0) -> 1
A26: Payments | B26: =COUNTIF('Test Cases'!B3:B1000,A26) -> 2 | C26: =COUNTIFS('Test Cases'!B3:B1000,A26,'Test Cases'!I3:I1000,"Pass") -> 2 | D26: =COUNTIFS('Test Cases'!B3:B1000,A26,'Test Cases'!I3:I1000,"Fail") -> 0 | E26: =IFERROR(C26/B26,0) -> 1
A27: Reviews | B27: =COUNTIF('Test Cases'!B3:B1000,A27) -> 2 | C27: =COUNTIFS('Test Cases'!B3:B1000,A27,'Test Cases'!I3:I1000,"Pass") -> 2 | D27: =COUNTIFS('Test Cases'!B3:B1000,A27,'Test Cases'!I3:I1000,"Fail") -> 0 | E27: =IFERROR(C27/B27,0) -> 1
A28: Profile Management | B28: =COUNTIF('Test Cases'!B3:B1000,A28) -> 2 | C28: =COUNTIFS('Test Cases'!B3:B1000,A28,'Test Cases'!I3:I1000,"Pass") -> 2 | D28: =COUNTIFS('Test Cases'!B3:B1000,A28,'Test Cases'!I3:I1000,"Fail") -> 0 | E28: =IFERROR(C28/B28,0) -> 1
A29: Admin Dashboard & Reports | B29: =COUNTIF('Test Cases'!B3:B1000,A29) -> 3 | C29: =COUNTIFS('Test Cases'!B3:B1000,A29,'Test Cases'!I3:I1000,"Pass") -> 3 | D29: =COUNTIFS('Test Cases'!B3:B1000,A29,'Test Cases'!I3:I1000,"Fail") -> 0 | E29: =IFERROR(C29/B29,0) -> 1
A30: Responsive UI | B30: =COUNTIF('Test Cases'!B3:B1000,A30) -> 3 | C30: =COUNTIFS('Test Cases'!B3:B1000,A30,'Test Cases'!I3:I1000,"Pass") -> 3 | D30: =COUNTIFS('Test Cases'!B3:B1000,A30,'Test Cases'!I3:I1000,"Fail") -> 0 | E30: =IFERROR(C30/B30,0) -> 1
A31: API Documentation | B31: =COUNTIF('Test Cases'!B3:B1000,A31) -> 1 | C31: =COUNTIFS('Test Cases'!B3:B1000,A31,'Test Cases'!I3:I1000,"Pass") -> 1 | D31: =COUNTIFS('Test Cases'!B3:B1000,A31,'Test Cases'!I3:I1000,"Fail") -> 0 | E31: =IFERROR(C31/B31,0) -> 1

Sheet Test Cases
A1: SmartCart — Detailed Test Cases
A2: Test Case ID | B2: Module | C2: Test Scenario | D2: Preconditions | E2: Test Steps | F2: Test Data | G2: Expected Result | H2: Actual Result | I2: Status | J2: Priority | K2: Remarks
A3: TC-001 | B3: Authentication | C3: Register a new customer with valid details | D3: No account exists for the given email | E3: 1. Go to Register page 2. Enter name, email, password 3. Submit the form | F3: name=Aarav Sharma; email=aarav.test@example.com; password=Test@123 | G3: Account is created; success message shown; user redirected to Login | H3: As Expected | I3: Pass | J3: High | K3: -
A4: TC-002 | B4: Authentication | C4: Register with an email already in use | D4: An account already exists with the given email | E4: 1. Go to Register page 2. Enter an already-registered email 3. Submit | F4: email=aarav.test@example.com (existing) | G4: 400 Bad Request – “User already exists”; no duplicate account created | H4: As Expected | I4: Pass | J4: High | K4: -
A5: TC-003 | B5: Authentication | C5: Register with an invalid email format | D5: - | E5: 1. Go to Register page 2. Enter a malformed email 3. Submit | F5: email=aarav_at_example | G5: Field-level validation error shown; request rejected before reaching the server | H5: As Expected | I5: Pass | J5: Medium | K5: -
A6: TC-004 | B6: Authentication | C6: Register with a password shorter than 6 characters | D6: - | E6: 1. Go to Register page 2. Enter a 4-character password 3. Submit | F6: password=abcd | G6: 400 Bad Request – “Password must be at least 6 characters” | H6: As Expected | I6: Pass | J6: Medium | K6: -
A7: TC-005 | B7: Authentication | C7: Login with correct credentials | D7: Registered account exists | E7: 1. Go to Login page 2. Enter registered email and correct password 3. Submit | F7: email=aarav.test@example.com; password=Test@123 | G7: 200 OK; signed JWT returned; user redirected to Products page | H7: As Expected | I7: Pass | J7: High | K7: -
A8: TC-006 | B8: Authentication | C8: Login with an incorrect password | D8: Registered account exists | E8: 1. Go to Login page 2. Enter registered email with a wrong password 3. Submit | F8: email=aarav.test@example.com; password=WrongPass1 | G8: 401 Unauthorized – invalid credentials; no token issued | H8: As Expected | I8: Pass | J8: High | K8: -
A9: TC-007 | B9: Security & Authorization | C9: Call a protected endpoint without a JWT | D9: User is logged out / no token stored | E9: 1. Call GET /api/cart directly (e.g., via Postman) with no Authorization header | F9: No Authorization header | G9: 401/403 response; access denied | H9: As Expected | I9: Pass | J9: High | K9: -
A10: TC-008 | B10: Security & Authorization | C10: Call a protected endpoint with an expired/invalid token | D10: - | E10: 1. Send a request with a malformed or expired JWT in the Authorization header | F10: Authorization: Bearer invalid.token.value | G10: 401 Unauthorized; request rejected by the JWT filter before reaching the controller | H10: As Expected | I10: Pass | J10: High | K10: -
A11: TC-009 | B11: Security & Authorization | C11: Customer account attempts to call an Admin-only endpoint | D11: Logged in as a CUSTOMER role account | E11: 1. Log in as a customer 2. Call an admin endpoint, e.g. POST /api/products | F11: Role=CUSTOMER | G11: 403 Forbidden; RBAC (@PreAuthorize) blocks the request | H11: As Expected | I11: Pass | J11: High | K11: -
A12: TC-010 | B12: Security & Authorization | C12: Verify passwords are stored hashed, not in plain text | D12: Access to the users table | E12: 1. Register a new account 2. Inspect the password column in the users table | F12: password=Test@123 | G12: Stored value is a BCrypt hash (e.g., starting with $2a$/$2b$), never the plaintext password | H12: As Expected | I12: Pass | J12: High | K12: -
A13: TC-011 | B13: Security & Authorization | C13: Cross-origin request from an unregistered origin | D13: - | E13: 1. Attempt an API call from an origin other than the configured frontend URLs | F13: Origin: https://random-site.example.com | G13: Request blocked by CORS policy | H13: As Expected | I13: Pass | J13: Medium | K13: -
... A53: TC-051 | B53: API Documentation | C53: Swagger UI loads and lists all documented endpoints | D53: Backend is running | E53: 1. Navigate to /swagger-ui/index.html on the deployed backend | F53: - | G53: Interactive API documentation loads, listing all 15 controllers and their endpoints | H53: As Expected | I53: Pass | J53: Low | K53: -
